{
  "protocol": {
    "mqtt":{
    "serverAddress": "localhost",
    "port": 8080,
    "license": "PfA8IFBdtuVTr0jVVxHEI8uCYkoqt5wv6JMX3ooP_URrjwfwEAQkzNjfhs6n-eBy4NZzx5fp2cKtA-b08JYOAQ:3",
    "key":"bAsp5Kwp3BzXObBmjHl8erlN4_-FxYMj",
    "channel": "desense/",
    "protocolId": "MQIsdp",
    "protocolVersion": 3,
    "secure": false,
    "passphrase": "vNEO42Tkhq7V",
    "tls": {
          "key": "./certs/iotagent.key",
          "cert": "./certs/iotagent.crt",
          "ca": [ {"name": "./certs/ca.crt"} ]
      }
    }
  },
  "device":{
    "frequency": 5000,
    "duration": 10000000,
    "accelerate": 1,
    "sensors": [
        {"name": "temprature", "value": "UNIFORM(0, 100)"},
        {"name": "voltage", "value": "UNIFORM(85, 120)"},
        {"name": "current", "value": "UNIFORM(1000, 2000)"}
  
    ]
  }
  }
  